pogema_toolbox/__init__.py
pogema_toolbox/algorithm_config.py
pogema_toolbox/config_variant_generator.py
pogema_toolbox/create_env.py
pogema_toolbox/eval_utils.py
pogema_toolbox/evaluator.py
pogema_toolbox/fix_num_threads_issue.py
pogema_toolbox/moving_ai_ingestion.py
pogema_toolbox/registry.py
pogema_toolbox/results_holder.py
pogema_toolbox/run_episode.py
pogema_toolbox/generators/__init__.py
pogema_toolbox/generators/generator_utils.py
pogema_toolbox/generators/maze_generator.py
pogema_toolbox/generators/random_generator.py
pogema_toolbox/generators/warehouse_generator.py
pogema_toolbox/maps/default-maps.yaml
pogema_toolbox/views/__init__.py
pogema_toolbox/views/view_multi_plot.py
pogema_toolbox/views/view_plot.py
pogema_toolbox/views/view_tabular.py
pogema_toolbox/views/view_utils.py
pogema_toolbox-0.1.1.dist-info/LICENSE
pogema_toolbox-0.1.1.dist-info/METADATA
pogema_toolbox-0.1.1.dist-info/WHEEL
pogema_toolbox-0.1.1.dist-info/top_level.txt
pogema_toolbox-0.1.1.dist-info/RECORD
