Metadata-Version: 2.1
Name: pogema-toolbox
Version: 0.1.1
Summary: Evaluation toolbox for Pogema environment
Home-page: https://github.com/Tviskaron/pogema-toolbox
Author: Alexey Skrynnik
License: Apache License 2.0
Requires-Python: >=3.8
License-File: LICENSE
Requires-Dist: loguru <=0.7.2
Requires-Dist: wandb <=0.13.4,>=0.12.9
Requires-Dist: matplotlib <=3.8.3
Requires-Dist: seaborn ~=0.13.2
Requires-Dist: tabulate <=0.8.10,>=0.8.7
Requires-Dist: importlib-metadata ==4.13.0
Requires-Dist: dask[distributed]
Requires-Dist: pydantic <=1.9.1,>=1.8.2
Requires-Dist: numpy >=1.21
Requires-Dist: pandas <=2.2.1
Requires-Dist: PyYAML <=6.0.1
Requires-Dist: pogema >=1.3.0
